__init__.py
bregman/__init__.py
bregman/densities.py
bregman/latent_pod.py
bregman/models.py
bregman/optimizers.py
bregman/regularizers.py
bregman/simplify.py
bregman/sparsify.py
bregman_learning-0.0.0.dist-info/AUTHORS.rst
bregman_learning-0.0.0.dist-info/LICENSE
bregman_learning-0.0.0.dist-info/METADATA
bregman_learning-0.0.0.dist-info/WHEEL
bregman_learning-0.0.0.dist-info/top_level.txt
bregman_learning-0.0.0.dist-info/RECORD
