Metadata-Version: 2.1
Name: bregman-learning
Version: 0.0.0
Summary: A pytorch extension providing the Bregman optimizers
Home-page: https://github.com/TJHeeringa/bregman-learning
Author: Tjeerd Jan Heeringa
Author-email: t.j.heeringa@utwente.nl
License: BSD-3-Clause
Project-URL: Documentation, https://bregman-learning.readthedocs.io/
Project-URL: Changelog, https://bregman-learning.readthedocs.io/en/latest/changelog.html
Project-URL: Issue Tracker, https://github.com/TJHeeringa/bregman-learning/issues
Classifier: Development Status :: 5 - Production/Stable
Classifier: Intended Audience :: Developers
Classifier: License :: OSI Approved :: BSD License
Classifier: Operating System :: Unix
Classifier: Operating System :: POSIX
Classifier: Operating System :: Microsoft :: Windows
Classifier: Operating System :: MacOS
Classifier: Programming Language :: Python
Classifier: Programming Language :: Python :: 3
Classifier: Programming Language :: Python :: 3 :: Only
Classifier: Programming Language :: Python :: 3.10
Classifier: Programming Language :: Python :: 3.11
Classifier: Programming Language :: Python :: 3.12
Classifier: Programming Language :: Python :: Implementation :: CPython
Classifier: Programming Language :: Python :: Implementation :: PyPy
Classifier: Topic :: Utilities
Requires-Python: >=3.10
License-File: LICENSE
License-File: AUTHORS.rst
Requires-Dist: torch >=1.12.0
Requires-Dist: numpy >=1.22.4
Requires-Dist: igraph
Requires-Dist: torch-simplify
Requires-Dist: numpy ==1.26 ; platform_system == "Windows"
